easypubsub/__init__.py
easypubsub/decorator.py
easypubsub/logging.py
easypubsub/proxy.py
easypubsub/publisher.py
easypubsub/py.typed
easypubsub/subscriber.py
easypubsub-0.4.3.dist-info/LICENSE
easypubsub-0.4.3.dist-info/METADATA
easypubsub-0.4.3.dist-info/WHEEL
easypubsub-0.4.3.dist-info/top_level.txt
easypubsub-0.4.3.dist-info/RECORD
