Metadata-Version: 2.1
Name: easypubsub
Version: 0.4.3
Summary: A simple wrapper around PyZMQ that provides an easy interface to Publish Subscribe.
Author: Matteo Pompili
Project-URL: Home, https://github.com/matpompili/easypubsub
Project-URL: Documentation, https://easypubsub.readthedocs.io/
Project-URL: Changelog, https://github.com/matpompili/easypubsub/blob/main/CHANGELOG.md
Classifier: Programming Language :: Python :: 3
Classifier: License :: OSI Approved :: MIT License
Classifier: Operating System :: OS Independent
Classifier: Intended Audience :: Developers
Classifier: Topic :: Software Development :: Libraries :: Python Modules
Requires-Python: >=3.8
License-File: LICENSE
Requires-Dist: pyzmq (>=23.2)
